teshort/__init__.py
teshort/teshort.py
teshort-0.0.2.dist-info/METADATA
teshort-0.0.2.dist-info/WHEEL
teshort-0.0.2.dist-info/top_level.txt
teshort-0.0.2.dist-info/RECORD
