Metadata-Version: 2.1
Name: teshort
Version: 0.0.2
Summary: Transformer-based item reduction tool
Home-page: https://github.com/sdoublej/teshort/master
Author: humansdoublej
Author-email: humansdoublej@naver.com
License: MIT
Classifier: Programming Language :: Python :: 3
Classifier: License :: OSI Approved :: MIT License
Classifier: Operating System :: OS Independent
Requires-Python: >=3.7
Requires-Dist: sentence-transformers
Requires-Dist: scikit-learn
Requires-Dist: matplotlib
Requires-Dist: pandas
Requires-Dist: numpy
Requires-Dist: umap-learn
